{"station": "Matsuyama", "date": "2026-06-15", "issued": "2026-06-13 00:00 JST", "committed_before_day": true, "hours": ["06:00", "07:00", "08:00"], "v14": [111.4, 249.9, 380.1], "p10": [43.2, 146.9, 220.9], "p90": [163.8, 342.8, 497.9], "truth": [null, null, null], "jma": [29.0, 138.0, 296.0], "v15": [115.6, 239.6, null], "v15_bt": false, "v15_p10": [null, null, null], "v15_p90": [null, null, null], "v15_ribbon_bt": false, "v15_issued": "2026-06-13 00:00 JST", "ecmwf": [51.0, 188.0, 340.0], "gfs": [20.0, 65.0, 51.0], "jma_p10": [0.0, 51.1, 63.2], "jma_p90": [261.2, 370.2, 558.7]}